{
  "note": "Deterministic queue-simulator fallback; not thesis SUMO reproduction.",
  "summaries": [
    {
      "scenario": "scenario1_low_demand",
      "policy": "semi_coordinated_rl",
      "eval_episodes": 10,
      "platoon_progression_percentage": null,
      "platoon_progression_note": "undefined: deterministic fallback has aggregate queues, not vehicle IDs/corridor crossings",
      "mean_average_travel_time_seconds": 121.25,
      "mean_total_stop_events": 25.2,
      "mean_observed_vehicles": 4.0,
      "mean_completed_vehicles": 314.7,
      "mean_average_stops_per_observed_vehicle": 6.3,
      "mean_reward": -208.5,
      "mean_mean_queue": 0.3475
    },
    {
      "scenario": "scenario1_low_demand",
      "policy": "independent_rl_local",
      "eval_episodes": 10,
      "platoon_progression_percentage": null,
      "platoon_progression_note": "undefined: deterministic fallback has aggregate queues, not vehicle IDs/corridor crossings",
      "mean_average_travel_time_seconds": 121.25,
      "mean_total_stop_events": 25.5,
      "mean_observed_vehicles": 4.0,
      "mean_completed_vehicles": 314.7,
      "mean_average_stops_per_observed_vehicle": 6.375,
      "mean_reward": -208.6,
      "mean_mean_queue": 0.347667
    },
    {
      "scenario": "scenario1_low_demand",
      "policy": "independent_fixed_ns",
      "eval_episodes": 10,
      "platoon_progression_percentage": null,
      "platoon_progression_note": "undefined: deterministic fallback has aggregate queues, not vehicle IDs/corridor crossings",
      "mean_average_travel_time_seconds": 575.25,
      "mean_total_stop_events": 2.0,
      "mean_observed_vehicles": 4.0,
      "mean_completed_vehicles": 133.1,
      "mean_average_stops_per_observed_vehicle": 0.5,
      "mean_reward": -54539.4,
      "mean_mean_queue": 90.899
    },
    {
      "scenario": "scenario1_low_demand",
      "policy": "cyclic_queue_backpressure",
      "eval_episodes": 10,
      "platoon_progression_percentage": null,
      "platoon_progression_note": "undefined: deterministic fallback has aggregate queues, not vehicle IDs/corridor crossings",
      "mean_average_travel_time_seconds": 162.5,
      "mean_total_stop_events": 31.3,
      "mean_observed_vehicles": 4.0,
      "mean_completed_vehicles": 318.0,
      "mean_average_stops_per_observed_vehicle": 7.825,
      "mean_reward": -135.4,
      "mean_mean_queue": 16.925
    },
    {
      "scenario": "scenario2_high_demand",
      "policy": "semi_coordinated_rl",
      "eval_episodes": 10,
      "platoon_progression_percentage": null,
      "platoon_progression_note": "undefined: deterministic fallback has aggregate queues, not vehicle IDs/corridor crossings",
      "mean_average_travel_time_seconds": 124.75,
      "mean_total_stop_events": 125.4,
      "mean_observed_vehicles": 4.0,
      "mean_completed_vehicles": 818.7,
      "mean_average_stops_per_observed_vehicle": 31.35,
      "mean_reward": -1068.4,
      "mean_mean_queue": 1.780667
    },
    {
      "scenario": "scenario2_high_demand",
      "policy": "independent_rl_local",
      "eval_episodes": 10,
      "platoon_progression_percentage": null,
      "platoon_progression_note": "undefined: deterministic fallback has aggregate queues, not vehicle IDs/corridor crossings",
      "mean_average_travel_time_seconds": 124.75,
      "mean_total_stop_events": 133.7,
      "mean_observed_vehicles": 4.0,
      "mean_completed_vehicles": 818.7,
      "mean_average_stops_per_observed_vehicle": 33.425,
      "mean_reward": -1060.3,
      "mean_mean_queue": 1.767167
    },
    {
      "scenario": "scenario2_high_demand",
      "policy": "independent_fixed_ns",
      "eval_episodes": 10,
      "platoon_progression_percentage": null,
      "platoon_progression_note": "undefined: deterministic fallback has aggregate queues, not vehicle IDs/corridor crossings",
      "mean_average_travel_time_seconds": 1220.25,
      "mean_total_stop_events": 2.0,
      "mean_observed_vehicles": 4.0,
      "mean_completed_vehicles": 380.5,
      "mean_average_stops_per_observed_vehicle": 0.5,
      "mean_reward": -132026.7,
      "mean_mean_queue": 220.0445
    },
    {
      "scenario": "scenario2_high_demand",
      "policy": "cyclic_queue_backpressure",
      "eval_episodes": 10,
      "platoon_progression_percentage": null,
      "platoon_progression_note": "undefined: deterministic fallback has aggregate queues, not vehicle IDs/corridor crossings",
      "mean_average_travel_time_seconds": 1075.5,
      "mean_total_stop_events": 5.0,
      "mean_observed_vehicles": 4.0,
      "mean_completed_vehicles": 494.8,
      "mean_average_stops_per_observed_vehicle": 1.25,
      "mean_reward": -1779.2,
      "mean_mean_queue": 222.4
    }
  ]
}